aws_finops_mcp_server/__init__.py
aws_finops_mcp_server/main.py
aws_finops_mcp_server/helpers/util.py
aws_finops_mcp_server-0.1.1.dist-info/licenses/LICENSE
aws_finops_mcp_server-0.1.1.dist-info/METADATA
aws_finops_mcp_server-0.1.1.dist-info/WHEEL
aws_finops_mcp_server-0.1.1.dist-info/entry_points.txt
aws_finops_mcp_server-0.1.1.dist-info/top_level.txt
aws_finops_mcp_server-0.1.1.dist-info/RECORD
