Metadata-Version: 2.4
Name: aws-finops-mcp-server
Version: 0.1.1
Summary: An MCP server for AWS FinOps to analyze costs and audit for savings.
Author: Ravi Kiran Vallamkonda
License-Expression: MIT
Project-URL: Homepage, https://github.com/ravikiranvm/aws-finops-mcp-server
Project-URL: Source, https://github.com/ravikiranvm/aws-finops-mcp-server
Keywords: aws,cost,finops,cloud
Requires-Python: >=3.10
License-File: LICENSE
Requires-Dist: boto3
Requires-Dist: mcp[cli]
Dynamic: license-file
